{"ALTERNATOR[A]":2850,"Angel's Ladder[A]":2609,"Don't believe the hype[A]":2413,"Fegrix[A]":2529,"GiGaGaHell[A]":1422,"LIVE DRIVING!! feat. 花たん[A]":3162,"One for All[A]":2435,"Purple Perplex[A]":950,"Skreaming for Salvation[A]":2328,"TOMAHAWK[A]":1282,"Triple Cross[A]":2664,"禊[A]":2478,"-65℃[A]":2676,"COSMIC RAY[A]":1922,"Ignis†Irae[A]":2426,"Level 3[A]":2666,"MEGAERA[A]":2494,"Sinus Iridum[A]":1603,"THE PEERLESS UNDER HEAVEN[A]":2404,"Tiempo Loco[A]":2818,"rommmo[A]":2645,"∀[A]":2630,"バッド・スイーツ、バッド・ドリーム[A]":2759,"世界の果てに約束の凱歌を -ReUnion-[A]":2903,"二人ノ廃城幽踊宴[A]":2541,"閠槞彁の願い[A]":2458,"Artist[A]":2659,"BEAT PRISONER[A]":2703,"Dans la nuit de l'eternite[A]":2216,"Double Dribble[A]":2691,"EROICA[A]":2990,"Everlasting Message[A]":2708,"Inferno of Fomalhaut[A]":2187,"LIGHTNING STRIKES[A]":2700,"Level 2[A]":2008,"Lords Of The Roundtable[A]":2092,"Megalara Garuda[A]":2304,"Primitive Vibes[A]":2254,"SCREW // owo // SCREW[A]":2350,"Smashing Wedge[A]":2878,"T-REX vs Velociraptor (In the Far east euphoria)[A]":2515,"TECHNO Style Essentials[A]":2171,"THE BRAVE MUST DIE[A]":2957,"THE F∀UST[A]":2578,"TRIUMPH[A]":2658,"がっつり陰キャ!? 怪盗いいんちょの億劫^^;[A]":3160,"ピアノ協奏曲第1番”蠍火” (BlackY Remix)[A]":2789,"華麗なる大犬円舞曲[A]":2213,"Carmina[A]":2828,"Carry Me Away[A]":2474,"Catch Our Fire![A]":2871,"Dr. Chemical & Killing Machine[A]":2618,"GENE[A]":3306,"GO OVER WITH GLARE -ROOTAGE 26-[A]":2873,"HARD BRAIN[A]":2914,"L.F.O[A]":2567,"Lethal Weapon[A]":2528,"Level One[A]":2532,"Macho Monky[A]":2255,"Painful Fate[A]":2475,"Red. by Jack Trance[A]":2503,"Visterhv[A]":2812,"dAuntl3ss[A]":2775,"お菓子の王国[A]":3059,"抱きしめてモナムール[A]":3177,"金野火織の金色提言[A]":2507,"255[A]":2221,"Antigravity[A]":2208,"Boomy and The Boost[A]":2822,"DEADHEAT[A]":2509,"DEATH†ZIGOQ ～怒りの高速爆走野郎～[A]":2603,"DropZ-Line-[A]":1274,"EMERALDAS[A]":2404,"Initiation[A]":2649,"Life Is A Game ft.DD\"ナカタ\"Metal[A]":2531,"Papilio ulysses[A]":2187,"Rampage[A]":3049,"encounter[A]":2437,"シムルグの目醒め[A]":2584,"東京神話[A]":2128,"#MAGiCVLGiRL_TRVP_B3VTZ[A]":2950,"Apocalypse[A]":2779,"DORNWALD ～Junge～[A]":2663,"ECHIDNA[A]":2504,"FUZIN RIZIN[A]":3058,"GuNGNiR[A]":2851,"HADES[A]":2495,"Quakes[A]":2334,"Rave Cannon[A]":2375,"SAY BAY[A]":2129,"Sky High[A]":2710,"Snakey Kung-fu[A]":2710,"Steel Edge[A]":2608,"Summerlights(IIDX Edition)[A]":2442,"Super Rush[A]":2938,"Venom[A]":2656,"イザナミノナゲキ[A]":2700,"刃図羅[A]":2603,"津軽雪[A]":2916,"焔極OVERKILL[A]":2781,"199024club -Re:BounceKiller-[A]":1722,"AO-1[A]":2181,"Blue Spring Express[A]":2579,"CODE:1 [revision1.0.1][A]":2399,"Devil's Gear[A]":2633,"Dynamite[A]":2906,"Godspeed[A]":2421,"Highcharge Divolt[A]":2266,"Konzert V[A]":2700,"M4K3 1T B0UNC3[A]":2539,"NZM[A]":2490,"Nightmare before oversleep[A]":2485,"POSSESSION[A]":2328,"Triple Counter[A]":2670,"X[A]":2585,"ZEPHYRANTHES[L]":2732,"めいさいアイドル☆あいむちゃん♪[A]":2694,"真 地獄超特急 -HELL or HELL-[A]":2444,"紫陽花 -AZISAI-[A]":2192,"駅猫のワルツ[A]":2003,"BLUE MIRAGE[A]":2142,"Broken Sword[A]":2920,"CHRONO DIVER -NORNIR-[L]":3536,"Chrono Diver -PENDULUMs-[A]":2991,"Cosmic Cat[L]":2536,"Despair of ELFERIA[A]":3231,"FANTASTIC THREE[A]":2595,"Flashes[A]":2414,"Gravigazer[A]":2207,"IMPLANTATION[A]":1494,"Monopole.[A]":2536,"Rave*it!! Rave*it!! [A]":2532,"Reflux[A]":2443,"Say YEEEAHH[A]":2680,"Shooting Fireball[A]":2982,"Sounds Of Summer[A]":2314,"TIEFSEE[A]":2755,"TOXIC VIBRATION[A]":2795,"ZZ[A]":2402,"entelecheia[A]":2599,"fallen leaves -IIDX edition-[A]":2417,"共鳴遊戯の華[A]":2851,"千年ノ理[A]":2715,"千年ノ理[L]":3157,"夏色DIARY - L.E.D.-G STYLE MIX -[A]":2306,"少年は空を辿る[A]":2526,"超青少年ノ為ノ超多幸ナ超古典的超舞曲[L]":2263,"Adularia[A]":2128,"Ancient Scapes[L]":3124,"Close the World feat.a☆ru[A]":2585,"Close the World feat.a☆ru[L]":2699,"DARK LEGACY[A]":2947,"Feel The Beat[L]":2824,"IX[A]":2710,"KAISER PHOENIX[A]":2448,"KAISER PHOENIX[L]":2698,"Sigmund[A]":2742,"Sigmund[L]":2990,"VOX UP[A]":2534,"Verflucht[A]":2426,"invoker[A]":2590,"ra'am[A]":1917,"廿[L]":2488,"煉獄のエルフェリア[A]":2890,"疾風迅雷[A]":2280,"疾風迅雷[L]":2232,"Confiserie[A]":2512,"DAY DREAM[A]":1353,"Devilz Staircase[A]":2518,"Elemental Creation[A]":2718,"GAIA[A]":2628,"Hollywood Galaxy[A]":1945,"JOMANDA[A]":2425,"Liberation[A]":2924,"Plan 8[A]":2341,"STULTI[A]":2070,"Thor's Hammer[A]":1333,"Timepiece phase II[A]":2482,"Timepiece phase II (CN Ver.)[A]":2067,"Valanga[A]":2596,"Zirkfied[A]":2822,"ΕΛΠΙΣ[L]":2549,"たまゆら[A]":2278,"キャトられ恋はモ～モク[A]":2588,"シュレーディンガーの猫[A]":2588,"狂イ咲ケ焔ノ華[A]":2846,"音楽[A]":1866,"BLACK.by X-Cross Fade[A]":2336,"DIAVOLO[A]":2389,"Snake Stick[A]":1923,"TITANS RETURN[L]":1896,"The Limbo[A]":2616,"The Sampling Paradise[A]":2436,"Todestrieb[A]":2792,"WONDER WALKER[A]":2773,"YAKSHA[A]":2697,"天空の夜明け[A]":2920,"恋する☆宇宙戦争っ！！[A]":2743,"聖人の塔[A]":2178,"ALBIDA[A]":540,"Dances with Snow Fairies[A]":2311,"Watch Out Pt.2[A]":1973,"perditus†paradisus[A]":2540,"reunion[A]":2382,"灼熱Beach Side Bunny[A]":2040,"黒髪乱れし修羅となりて[A]":2554,"AIR RAID FROM THA UNDAGROUND[L]":1881,"Almagest[A]":2412,"Bad Maniacs[A]":2254,"EXUSIA[A]":2844,"G59[A]":2736,"GOLDEN CROSS[A]":2706,"Red. by Full Metal Jacket[A]":2294,"SOLID STATE SQUAD[A]":2874,"mosaic[A]":2792,"quell～the seventh slave～[A]":2340,"ワルツ第17番 ト短調”大犬のワルツ”[A]":2231,"3y3s[A]":2367,"Colorful Cookie[A]":2871,"不沈艦CANDY[A]":2531,"卑弥呼[A]":2721,"ICARUS[L]":2547,"MENDES[A]":2641,"PARANOiA ～HADES～[A]":1508,"少年A[A]":1752,"Candy Galy[A]":2914,"FIRE FIRE[A]":2125,"Fascination MAXX[A]":1154,"KAMAITACHI[L]":2757,"Sense 2007[A]":2190,"TRANOID[L]":1924,"CONTRACT[L]":2035,"DUE TOMORROW[A]":1285,"カゴノトリ～弐式～[A]":2048,"嘆きの樹[A]":2951,"SCREAM SQUAD[A]":1608,"Twelfth Style[L]":2381,"冥[A]":2448,"AA[A]":2883,"gigadelic[A]":1896,"ピアノ協奏曲第１番”蠍火”[A]":2103,"Innocent Walls[H]":1898,"Innocent Walls[A]":2149,"One More Lovely[A]":2176,"桜[A]":1525,"A[A]":1786,"V[A]":2335}