{"24h Endurance Race[A]":2780,"B.O.D.Y.[A]":3068,"BIGWAVERS[A]":3202,"Bad Encryption[A]":2454,"Beyond Evolution[A]":2838,"Chaotoxin[A]":3052,"Hat Surprise (Season 2)[A]":3158,"I[A]":3108,"LOUDER ROLLING THUNDER[A]":2827,"Level 4[A]":3068,"MAX 360[A]":2684,"Meissa[A]":2561,"No Border[A]":3307,"ONE AND ONLY[A]":2813,"Ou Legends[A]":2880,"Peaktime Booster[A]":2772,"RINNE[A]":3195,"Somnidiscotheque[A]":2434,"Super Freak[A]":3072,"TECHNOPHOBIA[A]":2574,"The Clown of 24stairs[A]":2756,"VOLAQUAS[A]":3342,"Xerulean[A]":2717,"[ ]DENTITY[A]":3281,"anthracene[A]":2907,"dica dica[A]":2670,"glacia[A]":2768,"kors k's How to make OTOGE CORE 「LONG」[A]":3208,"ぞうしょく！？マイデンティティ[A]":3320,"儚キ戀ノ幻想譚[A]":3227,"恋愛＝精度×認識力[A]":3037,"栄冠のカンパネラ[A]":2986,"神のシナリオ[A]":2789,"2 Beasts Unchained[A]":2831,"ABSOLUTE EVIL[A]":3131,"ALTERNATOR[A]":3315,"Aftermath[A]":3276,"Angel's Ladder[A]":2967,"Arkadia[A]":3138,"Binary Black Hole[A]":3245,"Don't believe the hype[A]":2764,"Fegrix[A]":2905,"Flying Castle[A]":3197,"GRAVITON[A]":3138,"GiGaGaHell[A]":2272,"LIVE DRIVING!! feat. 花たん[A]":3580,"One for All[A]":2943,"PLASMA SOUL NIGHT feat. Nana Takahashi / 709sec.[A]":3970,"Purple Perplex[A]":2584,"Push on Beats!～音ゲの国のeX-ストリーマー～[A]":2849,"RAGE feat.H14 of LEONAIR[A]":3029,"Silver Bullet[A]":2671,"Skreaming for Salvation[A]":2662,"Smalt #28598F[A]":2957,"TOMAHAWK[A]":2973,"Triple Cross[A]":2988,"WHA[A]":2905,"hard-wired[A]":2912,"n/a[A]":2626,"デモーニッシュ[L]":2827,"ハイテックトキオ[L]":2987,"ピアノ独奏無言歌 \"灰燼\"[A]":2571,"天邪鬼[A]":3030,"烽火連天の刃[A]":2875,"禊[A]":2793,"逆月[A]":3149,"雪上断火[A]":2728,"-65℃[A]":3078,"3!dolon Forc3[A]":2524,"ASIAN VIRTUAL REALITIES (MELTING TOGETHER IN DAZZLING DARKNESS)[A]":2788,"BIGソムタム[A]":3208,"BLACK or WHITE?[A]":3315,"Burning Flame[L]":3208,"COSMIC RAY[A]":2354,"DUAL STRIKER[A]":3474,"Empire of Fury[A]":2864,"Fire Beat[A]":2486,"Ignis†Irae[A]":2943,"LOCUS OF THE TRAVEL[A]":3055,"Level 3[A]":3083,"MEGAERA[A]":2815,"Parvati[A]":2528,"SOLID STATE SQUAD -RISEN RELIC REMIX-[A]":2972,"Sinus Iridum[A]":2252,"THE PEERLESS UNDER HEAVEN[A]":2928,"Tiempo Loco[A]":3194,"Viridian[A]":3023,"Vitrum[A]":3168,"innocent revolver[A]":3347,"rommmo[A]":3183,"∀[A]":3156,"スーパー戦湯ババンバーン[A]":3046,"ディスコルディア[A]":3029,"バッド・スイーツ、バッド・ドリーム[A]":3105,"世界の果てに約束の凱歌を -ReUnion-[A]":3406,"二人ノ廃城幽踊宴[A]":2697,"伐折羅-vajra-[A]":3005,"水鏡の異界[A]":2742,"閠槞彁の願い[A]":2550,"魔法のかくれんぼ[A]":2335,"AKASHIC BREAK[A]":3258,"Artist[A]":3051,"BEAT PRISONER[A]":3155,"Dans la nuit de l'eternite[A]":2888,"Double Dribble[A]":3121,"EROICA[A]":3247,"Everlasting Message[A]":3022,"Friction[!]Function[A]":2880,"Inferno of Fomalhaut[A]":2464,"LASER CRUSTER (IGNITE REMIX)[A]":3039,"LIGHTNING STRIKES[A]":2991,"Level 2[A]":2512,"Lords Of The Roundtable[A]":2723,"Matt Silver[A]":2883,"Megalara Garuda[A]":2809,"ORCA[A]":2888,"Override[L]":3659,"Primitive Vibes[A]":2820,"Rave Patroller[A]":3143,"SCREW // owo // SCREW[A]":2683,"Smashing Wedge[A]":3157,"T-REX vs Velociraptor (In the Far east euphoria)[A]":2914,"TECHNO Style Essentials[A]":2522,"THE BRAVE MUST DIE[A]":3612,"THE F∀UST[A]":3019,"TRIUMPH[A]":3081,"Vinculum stellarum[A]":3159,"Ypsilon[L]":3251,"がっつり陰キャ!? 怪盗いいんちょの億劫^^;[A]":3571,"ピアノ協奏曲第1番”蠍火” (BlackY Remix)[A]":3145,"深淵に捧ぐレクイエム[A]":2572,"華麗なる大犬円舞曲[A]":2761,"魅惑のYUMMYスイーツ[A]":2707,"Carmina[A]":2943,"Carry Me Away[A]":2924,"Catch Our Fire![A]":3281,"DRUNK MONKY[A]":1880,"Dr. Chemical &amp; Killing Machine[A]":3046,"Drastic Dramatic[A]":3191,"EVANESCENT[A]":3046,"GENE[A]":3815,"GO OVER WITH GLARE -ROOTAGE 26-[A]":3169,"HARD BRAIN[A]":3232,"KILL EACH OTHER[A]":3368,"L.F.O[A]":2960,"LOST TECHNOLOGIE[A]":3010,"Lethal Weapon[A]":2932,"Level One[A]":2894,"Macho Monky[A]":2399,"ONIGOROSHI[A]":2545,"Painful Fate[A]":2876,"Please Welcome Mr.C[A]":2713,"Red. by Jack Trance[A]":3120,"THE DAY OF JUBILATIONS[A]":3144,"The Rebellion of Sequencer[A]":2678,"Trill auf G[A]":2890,"Unbelief[A]":2637,"Visterhv[A]":3336,"X-DEN[A]":2920,"Xlo[A]":3199,"dAuntl3ss[A]":3103,"ruin of opals[A]":2641,"voltississimo[A]":3008,"お菓子の王国[A]":3604,"抱きしめてモナムール[A]":3721,"最小三倍完全数[A]":2307,"金野火織の金色提言[A]":2541,"龍王の霊廟(Mausoleum Of The Primal Dragon)[L]":3465,"255[A]":2684,"AA -rebuild-[A]":3165,"ANCHOR[A]":3071,"Antigravity[A]":2674,"Arca[A]":2902,"Boomy and The Boost[A]":3211,"DEADHEAT[A]":2996,"DEATH†ZIGOQ ～怒りの高速爆走野郎～[A]":3367,"DropZ-Line-[A]":1557,"EMERALDAS[A]":2873,"Illusionary Waterlily[A]":3157,"Initiation[A]":3111,"Life Is A Game ft.DD\"ナカタ\"Metal[A]":3080,"NITROUS CANNON[A]":3152,"Papilio ulysses[A]":2453,"Persephone[A]":2733,"REVOLVER[L]":2581,"Rampage[A]":3393,"Raspberry Railgun[A]":2869,"Slipstream[A]":2978,"The Chase[A]":1802,"Xperanza[A]":2898,"encounter[A]":2953,"シムルグの目醒め[A]":2860,"東京神話[A]":2401,"神謳 -RESONANCE-[A]":3502,"#MAGiCVLGiRL_TRVP_B3VTZ[A]":3164,"Amazing Mirage[L]":2842,"Apocalypse[A]":3307,"BroGamer[L]":4191,"Caterpillar[A]":2684,"DORNWALD ～Junge～[A]":2888,"ECHIDNA[A]":2644,"FUZIN RIZIN[A]":3458,"Go Ahead!![A]":2146,"GuNGNiR[A]":3161,"GuNGNiR[L]":3526,"HADES[A]":2657,"Mare Nectaris[A]":2783,"OTENAMI Hurricane[A]":2783,"Quakes[A]":2805,"RAIN[A]":2951,"Rave Cannon[A]":3053,"SAMURAI-Scramble[L]":2282,"SAY BAY[A]":2480,"Sky High[A]":3189,"Snakey Kung-fu[A]":3041,"Steel Edge[A]":2972,"Summerlights(IIDX Edition)[A]":2925,"Super Rush[A]":3333,"Sweet Clapper[L]":2771,"TOGAKUSHI[A]":2283,"Umbral[L]":2706,"Venom[A]":2968,"〆[A]":3353,"イザナミノナゲキ[A]":2997,"九尾狐夜行[A]":2683,"刃図羅[A]":3108,"津軽雪[A]":3352,"火影[A]":2376,"焔極OVERKILL[A]":3069,"童話回廊[A]":1604,"199024club -Re:BounceKiller-[A]":2073,"AO-1[A]":2578,"Blue Spring Express[A]":2725,"CODE:1 [revision1.0.1][A]":2601,"DIAMOND CROSSING[A]":2610,"Devil's Gear[A]":2942,"Dynamite[A]":3519,"Godspeed[A]":2666,"Grand Chariot[A]":3031,"Highcharge Divolt[A]":2564,"Konzert V[A]":2904,"M4K3 1T B0UNC3[A]":2761,"NINJA IS DEAD IIDX ver.[A]":2799,"NZM[A]":2815,"Nightmare before oversleep[A]":2689,"POSSESSION[A]":2750,"STARLIGHT DANCEHALL[L]":2994,"StrayedCatz[A]":2332,"Triple Counter[A]":3521,"Violet Pulse[L]":3147,"Welcome[L]":3032,"X[A]":3383,"ZEPHYRANTHES[L]":3202,"refrain[A]":3106,"めいさいアイドル☆あいむちゃん♪[A]":3052,"灼熱 Pt.2 Long Train Running[A]":2625,"真 地獄超特急 -HELL or HELL-[A]":2882,"紫陽花 -AZISAI-[A]":2556,"駅猫のワルツ[A]":2243,"BLUE MIRAGE[A]":2549,"Beat Radiance[L]":3441,"Broken Sword[A]":3368,"CHRONO DIVER -NORNIR-[L]":3688,"Chrono Diver -PENDULUMs-[A]":3364,"Cosmic Cat[L]":2971,"Despair of ELFERIA[A]":3731,"EBONY &amp; IVORY[A]":2732,"EBONY &amp; IVORY[L]":2834,"FANTASTIC THREE[A]":2934,"Flashes[A]":2703,"Gravigazer[A]":2656,"IMPLANTATION[A]":1755,"Invitation from Mr.C[A]":2415,"Monopole.[A]":3010,"NEO GENERATOR SEVEN[A]":3019,"Rave*it!! Rave*it!![A]":3012,"Reflux[A]":2685,"Say YEEEAHH[A]":2987,"Shooting Fireball[A]":3455,"Sounds Of Summer[A]":2714,"SpaceLand☆TOYBOX[A]":2704,"Symmetry[A]":2995,"TIEFSEE[A]":3179,"TOXIC VIBRATION[A]":3235,"The Least 100sec[A]":2359,"We're so Happy (P*Light Remix) IIDX ver.[A]":3430,"ZZ[A]":2752,"cinder[A]":2844,"entelecheia[A]":2977,"fallen leaves -IIDX edition-[A]":2960,"それは花火のような恋[A]":3487,"リリーゼと炎龍レーヴァテイン[A]":3171,"共鳴遊戯の華[A]":3128,"千年ノ理[A]":2943,"千年ノ理[L]":3662,"夏色DIARY - L.E.D.-G STYLE MIX -[A]":2704,"少年は空を辿る[A]":2717,"紅牡丹[A]":2643,"表裏一体！？怪盗いいんちょの悩み[A]":3270,"超青少年ノ為ノ超多幸ナ超古典的超舞曲[L]":3342,"ATHER[L]":2925,"Adularia[A]":2506,"Ancient Scapes[A]":3177,"Ancient Scapes[L]":3355,"BLUE DRAGON(雷龍RemixIIDX)[A]":3087,"Close the World feat.a☆ru[A]":3099,"Close the World feat.a☆ru[L]":3188,"DARK LEGACY[A]":3267,"Elektrick U-Phoria[L]":3265,"Feel The Beat[A]":3230,"Feel The Beat[L]":3329,"INSOMNIA[A]":2810,"IX[A]":3109,"Idola[A]":3299,"KAISER PHOENIX[A]":2823,"KAISER PHOENIX[L]":2761,"Last Dance[A]":2740,"PUNISHER[A]":3246,"Sigmund[A]":3138,"Sigmund[L]":3270,"VOX UP[A]":3218,"Verflucht[A]":2886,"Verflucht[L]":3425,"invoker[A]":2938,"invoker[L]":3162,"ra'am[A]":2386,"廿[L]":3074,"旋律のドグマ～Miserables～[A]":3562,"海神[A]":2854,"煉獄のエルフェリア[A]":2949,"疾風迅雷[A]":2497,"疾風迅雷[L]":2602,"轟け！恋のビーンボール！！[A]":3032,"Confiserie[A]":2850,"DAY DREAM[A]":1693,"Devilz Staircase[A]":2835,"Elemental Creation[A]":3408,"GAIA[A]":2902,"Hollywood Galaxy[A]":2381,"Illegal Function Call[L]":2693,"JOMANDA[A]":3049,"Liberation[A]":3261,"Little Star[A]":2794,"Plan 8[A]":2772,"Proof of the existence[A]":2715,"STULTI[A]":2151,"SYNC-ANTHEM[A]":3335,"Sol Cosine Job 2[A]":2770,"Thor's Hammer[A]":2220,"Timepiece phase II[A]":2643,"Timepiece phase II (CN Ver.)[A]":2368,"True Blue[A]":3324,"Valanga[A]":2961,"Zirkfied[A]":3101,"neu[A]":3564,"ΕΛΠΙΣ[A]":2859,"ΕΛΠΙΣ[L]":3060,"†渚の小悪魔ラヴリィ～レイディオ†(IIDX EDIT)[A]":3072,"お米の美味しい炊き方、そしてお米を食べることによるその効果。[L]":2885,"たまゆら[A]":2557,"アストライアの双皿[A]":2615,"キャトられ恋はモ～モク[A]":3320,"シュレーディンガーの猫[A]":3059,"トリカゴノ鳳凰[A]":3361,"仮想空間の旅人たち[L]":3450,"即席！脳直★ミュージックシステム[A]":3188,"狂イ咲ケ焔ノ華[A]":3300,"音楽[A]":2230,"龍と少女とデコヒーレンス[L]":2907,"BLACK.by X-Cross Fade[A]":2876,"DIAVOLO[A]":2507,"F[A]":3120,"HAERETICUS[A]":2657,"NNRT[A]":3197,"Phoenix[L]":3150,"QUANTUM TELEPORTATION[L]":3218,"Snake Stick[A]":2254,"TITANS RETURN[L]":2324,"The Limbo[A]":2911,"The Limbo[L]":3367,"The Sampling Paradise[A]":2705,"Thunderbolt[A]":3409,"Todestrieb[A]":3152,"WONDER WALKER[A]":3482,"YAKSHA[A]":3256,"fffff[A]":2737,"quaver♪[A]":3172,"君のハートにロックオン[L]":2505,"天空の夜明け[A]":3184,"子供の落書き帳[A]":2259,"恋する☆宇宙戦争っ！！[A]":3110,"聖人の塔[A]":2657,"ALBIDA[A]":2723,"Broken[A]":2853,"Dances with Snow Fairies[A]":2662,"New Castle Legions[A]":2400,"PARADISE LOST[A]":2692,"SPECIAL SUMMER CAMPAIGN![A]":2763,"Session 9 -Chronicles-[A]":2974,"Watch Out Pt.2[A]":2292,"perditus†paradisus[A]":3105,"reunion[A]":2814,"sakura storm[A]":2236,"灼熱Beach Side Bunny[A]":2416,"黒髪乱れし修羅となりて[A]":3103,"AIR RAID FROM THA UNDAGROUND[L]":2277,"Almagest[A]":2522,"Bad Maniacs[A]":2666,"DOMINION[A]":2992,"EXUSIA[A]":3286,"Evans[A]":2263,"G59[A]":3341,"GOLDEN CROSS[A]":3161,"Red. by Full Metal Jacket[A]":2769,"SOLID STATE SQUAD[A]":3243,"SOLID STATE SQUAD[L]":3012,"eRAseRmOToRpHAntOM[A]":2801,"mosaic[A]":2923,"quell～the seventh slave～[A]":2577,"ワルツ第17番 ト短調”大犬のワルツ”[A]":2292,"3y3s[A]":2771,"Arabian Rave Night[L]":3235,"B4U(BEMANI FOR YOU MIX)[L]":3682,"BITTER CHOCOLATE STRIKER[A]":3437,"Colorful Cookie[A]":3171,"Go Beyond!![A]":1726,"Kung-fu Empire[L]":3580,"Marie Antoinette[L]":2888,"Secrets[L]":3360,"THANK YOU FOR PLAYING[L]":2493,"Y&amp;Co. is dead or alive[A]":2361,"thunder HOUSE NATION Remix[L]":3211,"不沈艦CANDY[A]":3063,"卑弥呼[A]":2837,"Anisakis -somatic mutation type\"Forza\"-[L]":3227,"Blue Rain[L]":2802,"ICARUS[A]":2174,"ICARUS[L]":2980,"MENDES[A]":3020,"NEW GENERATION -もう、お前しか見えない-[L]":2938,"PARANOiA ～HADES～[A]":2154,"Ristaccia[A]":2493,"STEEL NEEDLE[L]":2755,"THE DEEP STRIKER[L]":3019,"TROOPERS[A]":2781,"Time to Air[L]":3278,"Ubertreffen[L]":2842,"four pieces of heaven[L]":2060,"oratio[A]":2717,"ミラージュ・レジデンス[L]":2692,"少年A[A]":2436,"華爛漫 -Flowers-[L]":2880,"Candy Galy[A]":3237,"FIRE FIRE[A]":2465,"Fascination MAXX[A]":2204,"GRID KNIGHT[L]":3180,"KAMAITACHI[L]":2863,"LASER CRUSTER[A]":2856,"Sense 2007[A]":2419,"TRANOID[L]":2478,"VANESSA[A]":1987,"VANESSA[L]":2489,"snow storm[L]":3066,"電人、暁に斃れる。[A]":2912,"CONTRACT[L]":2254,"Concertino in Blue[A]":2086,"DUE TOMORROW[A]":1659,"Ganymede[L]":2124,"waxing and wanding[L]":3630,"カゴノトリ～弐式～[A]":2379,"嘆きの樹[A]":3288,"Little Little Princess[L]":3544,"SCREAM SQUAD[A]":1840,"Scripted Connection⇒ A mix[A]":2646,"Scripted Connection⇒ A mix[L]":3022,"Twelfth Style[L]":2887,"rage against usual[A]":2530,"冥[A]":2853,"AA[A]":3272,"Be quiet[L]":2281,"FAKE TIME[A]":2241,"RED ZONE[L]":2814,"gigadelic[H]":1991,"gigadelic[A]":2262,"spiral galaxy[L]":3401,"ピアノ協奏曲第１番”蠍火”[A]":2313,"Innocent Walls[H]":2189,"Innocent Walls[A]":2372,"One More Lovely[A]":2545,"雪月花[A]":2239,"moon_child[A]":2336,"one or eight[A]":1984,"PLEASE DON'T GO[A]":2112,"桜[A]":1884,"A[A]":2283,"MAX 300[A]":2132,"Colors (radio edit)[A]":2180,"V[A]":2706}