{"24h Endurance Race[A]":1887,"B.O.D.Y.[A]":2902,"Bad Encryption[A]":2663,"Beyond Evolution[A]":2814,"Chaotoxin[A]":2856,"Hat Surprise (Season 2)[A]":2854,"I[A]":3060,"LOUDER ROLLING THUNDER[A]":2698,"Level 4[A]":2543,"MAX 360[A]":2536,"Meissa[A]":2281,"No Border[A]":3009,"ONE AND ONLY[A]":2722,"Ou Legends[A]":2730,"Peaktime Booster[A]":2249,"RINNE[A]":3061,"Somnidiscotheque[A]":2574,"Super Freak[A]":2535,"TECHNOPHOBIA[A]":2507,"The Clown of 24stairs[A]":2682,"VOLAQUAS[A]":3139,"Xerulean[A]":519,"[ ]DENTITY[A]":3284,"anthracene[A]":2884,"dica dica[A]":2423,"glacia[A]":2549,"kors k's How to make OTOGE CORE 「LONG」[A]":2013,"ぞうしょく！？マイデンティティ[A]":3092,"儚キ戀ノ幻想譚[A]":3006,"栄冠のカンパネラ[A]":3019,"神のシナリオ[A]":2634,"2 Beasts Unchained[A]":2755,"ABSOLUTE EVIL[A]":2959,"ALTERNATOR[A]":3228,"Angel's Ladder[A]":1965,"Arkadia[A]":3148,"Binary Black Hole[A]":3194,"Don't believe the hype[A]":952,"Flying Castle[A]":3015,"GRAVITON[A]":2883,"GiGaGaHell[A]":2546,"LIVE DRIVING!! feat. 花たん[A]":2219,"One for All[A]":2622,"PLASMA SOUL NIGHT feat. Nana Takahashi / 709sec.[A]":3769,"Purple Perplex[A]":992,"RAGE feat.H14 of LEONAIR[A]":2818,"Skreaming for Salvation[A]":2456,"Smalt #28598F[A]":3031,"TOMAHAWK[A]":2822,"Triple Cross[A]":2669,"WHA[A]":2705,"hard-wired[A]":3025,"n/a[A]":2526,"デモーニッシュ[L]":2430,"ハイテックトキオ[L]":2752,"ピアノ独奏無言歌 \"灰燼\"[A]":2258,"天邪鬼[A]":2672,"烽火連天の刃[A]":2722,"逆月[A]":3044,"雪上断火[A]":2404,"-65℃[A]":3165,"3!dolon Forc3[A]":2186,"ASIAN VIRTUAL REALITIES (MELTING TOGETHER IN DAZZLING DARKNESS)[A]":1572,"BIGソムタム[A]":2991,"BLACK or WHITE?[A]":3257,"COSMIC RAY[A]":2107,"DUAL STRIKER[A]":3101,"Empire of Fury[A]":2713,"Ignis†Irae[A]":2976,"LOCUS OF THE TRAVEL[A]":2836,"Level 3[A]":2784,"MEGAERA[A]":2971,"Parvati[A]":2459,"SOLID STATE SQUAD -RISEN RELIC REMIX-[A]":837,"Sinus Iridum[A]":2027,"THE PEERLESS UNDER HEAVEN[A]":1932,"Tiempo Loco[A]":3106,"innocent revolver[A]":1670,"rommmo[A]":3060,"∀[A]":3005,"ディスコルディア[A]":2879,"バッド・スイーツ、バッド・ドリーム[A]":2864,"世界の果てに約束の凱歌を -ReUnion-[A]":3354,"二人ノ廃城幽踊宴[A]":802,"閠槞彁の願い[A]":2377,"Artist[A]":2850,"BEAT PRISONER[A]":2979,"Dans la nuit de l'eternite[A]":2933,"Double Dribble[A]":2766,"EROICA[A]":3368,"Everlasting Message[A]":3119,"Friction[!]Function[A]":2777,"Inferno of Fomalhaut[A]":1861,"LASER CRUSTER (IGNITE REMIX)[A]":1622,"Level 2[A]":2222,"Lords Of The Roundtable[A]":2284,"Megalara Garuda[A]":2354,"Override[L]":3657,"Rave Patroller[A]":2916,"SCREW // owo // SCREW[A]":2561,"Smashing Wedge[A]":3017,"T-REX vs Velociraptor (In the Far east euphoria)[A]":1285,"THE BRAVE MUST DIE[A]":210,"Vinculum stellarum[A]":2856,"がっつり陰キャ!? 怪盗いいんちょの億劫^^;[A]":3622,"ピアノ協奏曲第1番”蠍火” (BlackY Remix)[A]":3202,"Carmina[A]":3053,"Catch Our Fire![A]":3000,"DRUNK MONKY[A]":1856,"GENE[A]":3724,"GO OVER WITH GLARE -ROOTAGE 26-[A]":3467,"KILL EACH OTHER[A]":3273,"L.F.O[A]":2789,"Level One[A]":860,"Painful Fate[A]":2459,"Red. by Jack Trance[A]":1136,"The Rebellion of Sequencer[A]":2343,"X-DEN[A]":1960,"Xlo[A]":3123,"dAuntl3ss[A]":3026,"voltississimo[A]":2997,"お菓子の王国[A]":3594,"金野火織の金色提言[A]":1031,"255[A]":2667,"AA -rebuild-[A]":3065,"ANCHOR[A]":2902,"Arca[A]":2562,"Boomy and The Boost[A]":2989,"DEADHEAT[A]":2807,"DEATH†ZIGOQ ～怒りの高速爆走野郎～[A]":2424,"DropZ-Line-[A]":857,"EMERALDAS[A]":2785,"Illusionary Waterlily[A]":2904,"Initiation[A]":3281,"NITROUS CANNON[A]":1162,"Papilio ulysses[A]":2328,"REVOLVER[L]":1187,"Rampage[A]":3210,"The Chase[A]":1401,"Xperanza[A]":2681,"シムルグの目醒め[A]":2833,"#MAGiCVLGiRL_TRVP_B3VTZ[A]":853,"Amazing Mirage[L]":1322,"BroGamer[L]":4036,"Caterpillar[A]":1746,"DORNWALD ～Junge～[A]":3143,"ECHIDNA[A]":2419,"FUZIN RIZIN[A]":3267,"Go Ahead!![A]":2028,"GuNGNiR[A]":3103,"GuNGNiR[L]":3570,"HADES[A]":2248,"Mare Nectaris[A]":2971,"OTENAMI Hurricane[A]":2642,"Quakes[A]":2623,"Rave Cannon[A]":2719,"SAMURAI-Scramble[L]":2001,"Sky High[A]":3245,"Snakey Kung-fu[A]":2825,"Steel Edge[A]":2774,"Super Rush[A]":2600,"Sweet Clapper[L]":2426,"Umbral[L]":2590,"Venom[A]":2731,"火影[A]":1338,"199024club -Re:BounceKiller-[A]":1142,"Blue Spring Express[A]":2787,"Dynamite[A]":3152,"Godspeed[A]":2366,"Grand Chariot[A]":2623,"Highcharge Divolt[A]":2431,"Konzert V[A]":2621,"M4K3 1T B0UNC3[A]":2240,"NZM[A]":2866,"POSSESSION[A]":2479,"Triple Counter[A]":3510,"X[A]":3042,"灼熱 Pt.2 Long Train Running[A]":2425,"真 地獄超特急 -HELL or HELL-[A]":918,"駅猫のワルツ[A]":1545,"BLUE MIRAGE[A]":455,"Broken Sword[A]":3059,"CHRONO DIVER -NORNIR-[L]":3831,"Chrono Diver -PENDULUMs-[A]":3505,"Despair of ELFERIA[A]":3763,"EBONY &amp; IVORY[L]":2050,"IMPLANTATION[A]":671,"Monopole.[A]":1347,"NEO GENERATOR SEVEN[A]":2836,"Rave*it!! Rave*it!![A]":2820,"Reflux[A]":2512,"Sounds Of Summer[A]":2508,"TIEFSEE[A]":2854,"The Least 100sec[A]":2350,"ZZ[A]":2473,"entelecheia[A]":2777,"fallen leaves -IIDX edition-[A]":2745,"共鳴遊戯の華[A]":3078,"千年ノ理[A]":2708,"千年ノ理[L]":3477,"夏色DIARY - L.E.D.-G STYLE MIX -[A]":2515,"少年は空を辿る[A]":2777,"超青少年ノ為ノ超多幸ナ超古典的超舞曲[L]":232,"ATHER[L]":1394,"Ancient Scapes[A]":2928,"Ancient Scapes[L]":3327,"BLUE DRAGON(雷龍RemixIIDX)[A]":2780,"DARK LEGACY[A]":3040,"Feel The Beat[A]":3067,"Feel The Beat[L]":3741,"IX[A]":3215,"Idola[A]":3145,"KAISER PHOENIX[A]":2642,"KAISER PHOENIX[L]":3275,"Sigmund[A]":2774,"Sigmund[L]":3343,"VOX UP[A]":3027,"Verflucht[A]":2567,"Verflucht[L]":3704,"廿[L]":1588,"煉獄のエルフェリア[A]":3264,"疾風迅雷[A]":2300,"疾風迅雷[L]":2664,"Confiserie[A]":3096,"DAY DREAM[A]":317,"Devilz Staircase[A]":2556,"Elemental Creation[A]":3467,"GAIA[A]":2783,"Hollywood Galaxy[A]":2023,"Illegal Function Call[L]":2958,"JOMANDA[A]":1018,"Liberation[A]":3111,"Plan 8[A]":1107,"STULTI[A]":18,"Thor's Hammer[A]":1432,"Timepiece phase II[A]":1579,"Timepiece phase II (CN Ver.)[A]":2245,"True Blue[A]":2736,"Valanga[A]":2538,"Zirkfied[A]":3171,"neu[A]":3229,"†渚の小悪魔ラヴリィ～レイディオ†(IIDX EDIT)[A]":2904,"お米の美味しい炊き方、そしてお米を食べることによるその効果。[L]":2968,"たまゆら[A]":2324,"アストライアの双皿[A]":1662,"シュレーディンガーの猫[A]":2777,"BLACK.by X-Cross Fade[A]":2498,"DIAVOLO[A]":2642,"F[A]":3065,"HAERETICUS[A]":2451,"Phoenix[L]":3223,"Snake Stick[A]":1415,"TITANS RETURN[L]":1977,"The Limbo[A]":2893,"The Limbo[L]":3589,"Todestrieb[A]":2671,"WONDER WALKER[A]":3243,"YAKSHA[A]":3096,"quaver♪[A]":2959,"君のハートにロックオン[L]":2763,"天空の夜明け[A]":3405,"子供の落書き帳[A]":2121,"聖人の塔[A]":303,"Broken[A]":2766,"Dances with Snow Fairies[A]":2579,"New Castle Legions[A]":1117,"PARADISE LOST[A]":2659,"Session 9 -Chronicles-[A]":2459,"perditus†paradisus[A]":3262,"sakura storm[A]":1818,"灼熱Beach Side Bunny[A]":2013,"AIR RAID FROM THA UNDAGROUND[L]":2520,"Almagest[A]":2452,"Bad Maniacs[A]":2749,"EXUSIA[A]":3223,"Evans[A]":2308,"G59[A]":3015,"GOLDEN CROSS[A]":2523,"Red. by Full Metal Jacket[A]":819,"SOLID STATE SQUAD[A]":3001,"eRAseRmOToRpHAntOM[A]":2448,"quell～the seventh slave～[A]":2714,"3y3s[A]":2806,"B4U(BEMANI FOR YOU MIX)[L]":3762,"BITTER CHOCOLATE STRIKER[A]":3237,"Colorful Cookie[A]":3029,"Go Beyond!![A]":1826,"Marie Antoinette[L]":2314,"Y&amp;Co. is dead or alive[A]":1565,"thunder HOUSE NATION Remix[L]":3267,"不沈艦CANDY[A]":2908,"卑弥呼[A]":2916,"ICARUS[A]":1400,"MENDES[A]":2648,"NEW GENERATION -もう、お前しか見えない-[L]":1501,"PARANOiA ～HADES～[A]":1941,"STEEL NEEDLE[L]":2811,"Time to Air[L]":3,"ミラージュ・レジデンス[L]":2690,"華爛漫 -Flowers-[L]":2638,"Fascination MAXX[A]":161,"KAMAITACHI[L]":3164,"Sense 2007[A]":2440,"VANESSA[A]":2079,"VANESSA[L]":896,"電人、暁に斃れる。[A]":2581,"Concertino in Blue[A]":1458,"Ganymede[L]":1631,"嘆きの樹[A]":2519,"Little Little Princess[L]":3502,"Scripted Connection⇒ A mix[A]":2483,"Scripted Connection⇒ A mix[L]":2602,"冥[A]":3051,"AA[A]":3201,"Be quiet[L]":1351,"FAKE TIME[A]":1815,"ピアノ協奏曲第１番”蠍火”[A]":2269,"Innocent Walls[H]":1755,"Innocent Walls[A]":2158,"One More Lovely[A]":2197,"moon_child[A]":2156,"PLEASE DON'T GO[A]":2069,"桜[A]":1667}