{"ACT0[A]":2838,"Ambivalent Vermilia[A]":3648,"BLAZING_LAZER[A]":3173,"CADENZA[A]":4152,"Cult Invitation[A]":3190,"Dahlia[A]":2945,"Demon March[A]":3441,"GAME ON[A]":2576,"Ghost Pulse[A]":2648,"Glitch N Ride[A]":2356,"JUSTICE/GUILTY feat. Nana Takahashi &amp; 709sec.[A]":3668,"Level 5[A]":3220,"MAXIMUM CHEAT GIRL[A]":3195,"Million Dollar[A]":3203,"Out of Control[A]":2858,"Resonant[A]":3317,"SOLAR ECLIPSE[A]":3154,"Sirius[A]":3061,"Stereo Beasts[A]":3508,"Sword of Vengeance[A]":3067,"The Last Apocalypse[A]":3471,"Vermilion Carol[A]":3389,"Vulnerability[A]":3297,"Xb10r[A]":3272,"frequent[A]":3530,"《PL|RAYER》[A]":2666,"今宵、ロマンス横丁。[A]":3130,"惑星鉄道[A]":2362,"摩天楼[A]":2357,"未完成ノ蒸氣驅動乙女[A]":2744,"残像ニ繋ガレタ追憶ノHIDEAWAY[A]":3383,"灼熱Beach Side Bunny (かめりあ's \"Summertime D'n'B\" Remix)[A]":2893,"終焔のClaudia[A]":2533,"電光[A]":2842,"電腦都市[A]":3153,"B.O.D.Y.[A]":3196,"BIGWAVERS[A]":3257,"Beyond Evolution[A]":3527,"KING[L]":3730,"Level 4[A]":3182}