{"ACT0[A]":2668,"Ambivalent Vermilia[A]":3227,"BLAZING_LAZER[A]":2999,"CADENZA[A]":3757,"Cult Invitation[A]":2943,"Dahlia[A]":2804,"Demon March[A]":3055,"GAME ON[A]":2513,"Ghost Pulse[A]":2496,"Glitch N Ride[A]":1975,"JUSTICE/GUILTY feat. Nana Takahashi &amp; 709sec.[A]":3558,"Level 5[A]":2952,"MAXIMUM CHEAT GIRL[A]":3171,"Million Dollar[A]":3009,"Out of Control[A]":2682,"Resonant[A]":2962,"SOLAR ECLIPSE[A]":2913,"Sirius[A]":2937,"Stereo Beasts[A]":3337,"Sword of Vengeance[A]":2983,"The Last Apocalypse[A]":3175,"Vermilion Carol[A]":3206,"Vulnerability[A]":3009,"Xb10r[A]":3044,"frequent[A]":3315,"《PL|RAYER》[A]":2577,"今宵、ロマンス横丁。[A]":2764,"惑星鉄道[A]":2178,"摩天楼[A]":2339,"未完成ノ蒸氣驅動乙女[A]":2445,"残像ニ繋ガレタ追憶ノHIDEAWAY[A]":3353,"灼熱Beach Side Bunny (かめりあ's \"Summertime D'n'B\" Remix)[A]":2740,"終焔のClaudia[A]":2414,"電光[A]":2670,"電腦都市[A]":3081,"#CMFLG[A]":2991,"24h Endurance Race[A]":2766,"Always We Trust In You[A]":2837,"B.O.D.Y.[A]":3072,"BIGWAVERS[A]":3124,"Bad Encryption[A]":2246,"Beyond Evolution[A]":2844,"Chaotoxin[A]":2998,"I[A]":3144,"KING[L]":3600,"LOUDER ROLLING THUNDER[A]":2806,"Level 4[A]":2959,"Meissa[A]":2543,"No Border[A]":3334,"ONE AND ONLY[A]":2661,"Ou Legends[A]":2802,"Peaktime Booster[A]":2785,"RINNE[A]":2959,"Somnidiscotheque[A]":2473,"Super Freak[A]":2871,"The Clown of 24stairs[A]":2815,"VOLAQUAS[A]":3307,"VØID[A]":2630,"Xerulean[A]":2792,"[ ]DENTITY[A]":3288,"anthracene[A]":2963,"glacia[A]":2706,"kors k's How to make OTOGE CORE 「LONG」[A]":3114,"suspicions[A]":3215,"ぞうしょく！？マイデンティティ[A]":3098,"儚キ戀ノ幻想譚[A]":3123,"栄冠のカンパネラ[A]":3079,"神のシナリオ[A]":2949,"2 Beasts Unchained[A]":2861,"ABSOLUTE EVIL[A]":2954,"ALTERNATOR[A]":3252,"Angel's Ladder[A]":2915,"Arkadia[A]":3046,"Binary Black Hole[A]":3110,"Don't believe the hype[A]":2777,"Fegrix[A]":2855,"Flying Castle[A]":3145,"GRAVITON[A]":2592,"GiGaGaHell[A]":2709,"LIVE DRIVING!! feat. 花たん[A]":3522,"One for All[A]":2870,"PLASMA SOUL NIGHT feat. Nana Takahashi / 709sec.[A]":3831,"Purple Perplex[A]":2558,"RAGE feat.H14 of LEONAIR[A]":3074,"SOLID WYVERN[L]":3176,"Silver Bullet[A]":2681,"Skreaming for Salvation[A]":2823,"Smalt #28598F[A]":2974,"TOMAHAWK[A]":3041,"Triple Cross[A]":2871,"WHA[A]":2896,"hard-wired[A]":2938,"n/a[A]":2550,"Super Rush[A]":3271,"Dynamite[A]":2931,"NINJA IS DEAD IIDX ver.[A]":2709,"Nightmare before oversleep[A]":2747,"Violet Pulse[L]":3136,"Rave*it!! Rave*it!![A]":2962,"Smashing Wedge[A]":2993,"THE F∀UST[A]":2910,"TRIUMPH[A]":2762,"がっつり陰キャ!? 怪盗いいんちょの億劫^^;[A]":3617,"ピアノ協奏曲第1番”蠍火” (BlackY Remix)[A]":3253,"俺ら東京さ行ぐだ[L]":2883,"深淵に捧ぐレクイエム[A]":2620,"CODE:0[L]":2850,"Carmina[A]":3002,"Carry Me Away[A]":2893,"Catch Our Fire![A]":3092,"Dr. Chemical &amp; Killing Machine[A]":2556,"GENE[A]":3672,"GO OVER WITH GLARE -ROOTAGE 26-[A]":3494,"KILL EACH OTHER[A]":3161,"L.F.O[A]":2958,"Level One[A]":2719,"Painful Fate[A]":2860,"The Rebellion of Sequencer[A]":2619,"Trill auf G[A]":2751,"Unbelief[A]":2425,"Visterhv[A]":3386,"ruin of opals[A]":2788,"voltississimo[A]":2749,"抱きしめてモナムール[A]":2210,"金野火織の金色提言[A]":2441,"龍王の霊廟(Mausoleum Of The Primal Dragon)[L]":3544,"255[A]":2974,"AA -rebuild-[A]":2974,"Antigravity[A]":2564,"Arca[A]":2772,"Boomy and The Boost[A]":3104,"DEATH†ZIGOQ ～怒りの高速爆走野郎～[A]":3286,"DropZ-Line-[A]":2601,"EMERALDAS[A]":2800,"Initiation[A]":3286,"Life Is A Game ft.DD\"ナカタ\"Metal[A]":3070,"NITROUS CANNON[A]":3168,"REVOLVER[L]":2498,"Rampage[A]":3346,"シムルグの目醒め[A]":2852,"東京神話[A]":2428,"神謳 -RESONANCE-[A]":3333,"#MAGiCVLGiRL_TRVP_B3VTZ[A]":3132,"Apocalypse[A]":3246,"BroGamer[L]":1236,"Caterpillar[A]":2657,"ECHIDNA[A]":2637,"Go Ahead!![A]":1949,"GuNGNiR[A]":1971,"GuNGNiR[L]":3002,"HADES[A]":2679,"Mare Nectaris[A]":2899,"Quakes[A]":2584,"RAIN[A]":2953,"SAMURAI-Scramble[L]":1979,"SAY BAY[A]":2549,"Sky High[A]":2158,"Snakey Kung-fu[A]":2958,"Steel Edge[A]":2939,"Sweet Clapper[L]":2699,"TOGAKUSHI[A]":2290,"Umbral[L]":2787,"〆[A]":3401,"イザナミノナゲキ[A]":3032,"九尾狐夜行[A]":2014,"刃図羅[A]":3139,"焔極OVERKILL[A]":2922,"199024club -Re:BounceKiller-[A]":2003,"Blue Spring Express[A]":2721,"DIAMOND CROSSING[A]":2637,"Devil's Gear[A]":2988,"Godspeed[A]":1068,"Highcharge Divolt[A]":2537,"M4K3 1T B0UNC3[A]":2702,"NZM[A]":2733,"POSSESSION[A]":2689,"STARLIGHT DANCEHALL[L]":2836,"Triple Counter[A]":3430,"Welcome[L]":1395,"X[A]":3245,"めいさいアイドル☆あいむちゃん♪[A]":3044,"真 地獄超特急 -HELL or HELL-[A]":2827,"駅猫のワルツ[A]":2394,"Beat Radiance[L]":3414,"Broken Sword[A]":3339,"CHRONO DIVER -NORNIR-[L]":2671,"Chrono Diver -PENDULUMs-[A]":2907,"Despair of ELFERIA[A]":3486,"EBONY &amp; IVORY[A]":1527,"EBONY &amp; IVORY[L]":1889,"Monopole.[A]":2943,"NEO GENERATOR SEVEN[A]":2935,"Reflux[A]":2602,"Shooting Fireball[A]":2980,"Sounds Of Summer[A]":2389,"SpaceLand☆TOYBOX[A]":2669,"Symmetry[A]":3015,"TIEFSEE[A]":3123,"ZZ[A]":2716,"entelecheia[A]":2747,"fallen leaves -IIDX edition-[A]":2906,"それは花火のような恋[A]":3462,"リリーゼと炎龍レーヴァテイン[A]":3247,"共鳴遊戯の華[A]":3097,"千年ノ理[A]":3024,"千年ノ理[L]":3617,"少年は空を辿る[A]":2872,"紅牡丹[A]":2601,"表裏一体！？怪盗いいんちょの悩み[A]":3247,"表裏一体！？怪盗いいんちょの悩み[L]":3721,"超青少年ノ為ノ超多幸ナ超古典的超舞曲[L]":2540,"ATHER[L]":2946,"Adularia[A]":2658,"Ancient Scapes[L]":833,"BLUE DRAGON(雷龍RemixIIDX)[A]":2995,"Close the World feat.a☆ru[A]":3041,"Close the World feat.a☆ru[L]":3152,"DARK LEGACY[A]":2816,"Elektrick U-Phoria[L]":3094,"Feel The Beat[A]":3195,"Feel The Beat[L]":3161,"IX[A]":3166,"KAISER PHOENIX[L]":2151,"Miracle 5ympho X[L]":1682,"VOX UP[A]":3141,"Verflucht[A]":2939,"Verflucht[L]":2774,"invoker[A]":2949,"invoker[L]":3061,"ra'am[A]":2341,"海神[A]":2850,"煉獄のエルフェリア[A]":3178,"Confiserie[A]":2650,"DAY DREAM[A]":1620,"Elemental Creation[A]":3207,"Illegal Function Call[L]":599,"JOMANDA[A]":3001,"Little Star[A]":2840,"Plan 8[A]":2816,"Proof of the existence[A]":2787,"SYNC-ANTHEM[A]":3311,"Thor's Hammer[A]":2391,"Timepiece phase II (CN Ver.)[A]":2253,"ΕΛΠΙΣ[A]":2878,"ΕΛΠΙΣ[L]":3008,"お米の美味しい炊き方、そしてお米を食べることによるその効果。[L]":1880,"キャトられ恋はモ～モク[A]":1234,"シュレーディンガーの猫[A]":3137,"仮想空間の旅人たち[L]":3462,"音楽[A]":2317,"龍と少女とデコヒーレンス[L]":2873,"BLACK.by X-Cross Fade[A]":2722,"DIAVOLO[A]":2607,"F[A]":3212,"Phoenix[L]":2176,"Snake Stick[A]":2259,"TITANS RETURN[L]":900,"The Limbo[A]":2969,"The Limbo[L]":1512,"The Sampling Paradise[A]":2686,"Thunderbolt[A]":3355,"Todestrieb[A]":3083,"WONDER WALKER[A]":3391,"yellow head joe[L]":2609,"君のハートにロックオン[L]":2884,"天空の夜明け[A]":3009,"子供の落書き帳[A]":2125,"恋する☆宇宙戦争っ！！[A]":1081,"恋する☆宇宙戦争っ！！[L]":3556,"聖人の塔[A]":2493,"ALBIDA[A]":2680,"Broken[A]":2880,"Dances with Snow Fairies[A]":2647,"New Castle Legions[A]":2459,"PARADISE LOST[A]":2805,"SPECIAL SUMMER CAMPAIGN![A]":2761,"Watch Out Pt.2[A]":2478,"perditus†paradisus[A]":3037,"reunion[A]":2874,"灼熱Beach Side Bunny[A]":2234,"AIR RAID FROM THA UNDAGROUND[L]":2628,"Almagest[A]":2515,"Bad Maniacs[A]":2216,"Evans[A]":2317,"GOLDEN CROSS[A]":3127,"Red. by Full Metal Jacket[A]":2599,"SOLID STATE SQUAD[A]":3111,"eRAseRmOToRpHAntOM[A]":2733,"mosaic[A]":2883,"ワルツ第17番 ト短調”大犬のワルツ”[A]":2907,"3y3s[A]":2815,"Arabian Rave Night[L]":3169,"BITTER CHOCOLATE STRIKER[A]":3704,"Go Beyond!![A]":1768,"Kung-fu Empire[L]":3416,"Marie Antoinette[L]":2902,"Secrets[L]":3523,"不沈艦CANDY[A]":2861,"卑弥呼[A]":2989,"Blue Rain[L]":1842,"ICARUS[A]":1954,"NEW GENERATION -もう、お前しか見えない-[L]":3069,"Ristaccia[A]":2564,"Time to Air[L]":1979,"four pieces of heaven[L]":940,"ミラージュ・レジデンス[L]":2931,"少年A[A]":1182,"華爛漫 -Flowers-[L]":2850,"Fascination MAXX[A]":2001,"GRID KNIGHT[L]":3368,"LASER CRUSTER[A]":2976,"snow storm[L]":3040,"Concertino in Blue[A]":2076,"カゴノトリ～弐式～[A]":2366,"嘆きの樹[A]":3298,"華蝶風雪[L]":3715,"Little Little Princess[L]":3491,"Twelfth Style[L]":2735,"rage against usual[A]":1731,"冥[A]":2821,"AA[A]":3362,"Be quiet[L]":2214,"gigadelic[H]":1943,"ピアノ協奏曲第１番”蠍火”[A]":2376,"moon_child[A]":2339,"桜[A]":1884,"A[A]":2144,"MAX 300[A]":2338}