{"3V0[A]":2483,"Move UR Body[A]":2232,"Perfect Plan[A]":2269,"Ruler or Loser[A]":2367,"Seraph[A]":2274,"Shadow World[A]":2547,"≡+≡[A]":2794,"いつかオトナになれるといいね。[A]":2846,"響花水月[A]":2652,"Souhait bleu[A]":2405,"グッバイ宣言[A]":2863,"シル・ヴ・プレジデント[L]":2461,"月とミルク[A]":2603,"青の洞窟[A]":2672,"Ypsilon[A]":2582,"バ→ビ→ブ→Bomb![A]":2277,"Amazing Mirage[A]":2135,"BroGamer[A]":2718,"パ→ピ→プ→Yeah![A]":2364,"超青少年ノ為ノ超多幸ナ超古典的超舞曲[A]":2544,"Ｘ↑Ｘ↓[A]":2521,"ALBA -黎明-[A]":2921,"Unicorn tail[A]":2732,"仮想空間の旅人たち[A]":2610,"Sakura Reflection[A]":2290,"Elisha[A]":2154,"Blue Rain[A]":2062,"Blind Justice ～Torn souls, Hurt Faiths ～[A]":2299,"GOLD RUSH[A]":2043,"Second Heaven[A]":1989,"waxing and wanding[A]":2769,"Little Little Princess[A]":2527,"KEY[A]":2668,"quasar[A]":2157,"R5[A]":1601}