{"3V0[A]":2585,"Ambush Ace[A]":2654,"Beyond Evolution[H]":2208,"C-C-C-N-N-N[A]":2456,"CODE -CRiMSON-[A]":2616,"Caldwell 99[A]":2189,"DIAMOND JACKAL[A]":2107,"EXODUS SIGN[A]":2245,"Get On Your Feet[A]":2422,"KING[A]":2855,"Move UR Body[A]":2177,"OVER VOLTAGE[A]":2093,"Perfect Plan[A]":1902,"Programmed Genom[A]":2170,"Red Soul[A]":2394,"Ruler or Loser[A]":2428,"STRAIGHT TO THE STARS[A]":2681,"Seraph[A]":2306,"Shadow World[A]":2552,"THE TIME MACHINE[A]":2332,"VOLCANIC BIGBEAT[A]":2387,"With You[A]":2206,"ZENITH[A]":2445,"≡+≡[A]":2735,"《ORDERBREAKER》[A]":2005,"あるビー！ feat.ころねぽち[A]":2550,"いつかオトナになれるといいね。[A]":2835,"ちょえちょえまぎか[A]":2778,"パーフェクトイーター[A]":2727,"マツケンサンバII[A]":2619,"輪廻の鴉[A]":2448,"響花水月[A]":2465,"10000 MILES AWAY[A]":2551,"DISPARATE[A]":2031,"Divine Heaven[A]":2606,"Ergosphere[A]":2225,"FINALLY BLAZE[A]":2373,"Game Changers[A]":2398,"Hat Surprise[A]":2216,"Lawes's Parotia[A]":2333,"Onyx[A]":2040,"Souhait bleu[A]":2079,"Tail Lights[A]":2732,"Victory Of Ravers[A]":2307,"kors k's How to make OTOGE CORE[A]":1963,"《GRANDMASTER》[A]":2539,"オールトの雲[A]":2424,"シル・ヴ・プレジデント[L]":2451,"デモーニッシュ[A]":2162,"月とミルク[A]":2527,"ABSOLUTE (kors k Remix)[A]":2115,"AMRITA -不滅ノ花-[A]":2544,"Ah Hah Yeah[A]":1848,"Brahma[A]":2376,"Burning Flame[A]":2427,"Crazy Jackpot[A]":2376,"Danza Aestas[A]":2573,"Dawn Saga[A]":2215,"GIGA RAID[A]":2139,"Globe Glitter[A]":2402,"Jungle Eater[A]":2555,"LAST DAY[A]":2659,"LIKE A VAMPIRE[A]":2522,"MA・TSU・RI[A]":2329,"Neo Heritage[A]":2586,"OTOKOZAKA[A]":2555,"Overslept[A]":2321,"Rejection Girl[A]":2224,"Ritual of Anubis[A]":2352,"Rosa azuL[A]":2220,"Rubrum Piano[A]":2228,"Scandal[A]":2373,"Sinus Iridum[H]":1811,"Tell me what you wish feat.らっぷびと[A]":2600,"Zenith[A]":1600,"of the first magnitude[A]":2623,"乱膳の舞姫[A]":2308,"儚き恋の華[A]":2705,"無意識のフィロソフィア[A]":2837,"27th style[A]":2172,"Bow shock!![A]":2814,"GHOST[A]":2385,"Into The Madness[A]":2019,"Like+it![A]":2135,"Moving on[A]":2684,"Override[A]":2608,"PHASE SHIFT MANEUVER[A]":2528,"Shiva[A]":1899,"Sparkle Smilin'[A]":2286,"VALKYRIAS -英雄誕生-[A]":2531,"シャムシールの舞[A]":2185,"バッドエンド・シンドローム[A]":2688,"ランカーキラーガール[A]":2718,"狂水一華[A]":2235,"眠りの国のステラ[A]":2371,"錬成人間トリコロイダー[A]":2922,"Ember Lights[A]":2440,"HEISEI[A]":2305,"Psycho Sheep Riddim[L]":1870,"ROCK女 feat. 大山愛未, Ken[A]":2278,"Wolf 1061[A]":2702,"X-DEN[H]":2007,"ZENDEGI DANCE[A]":2577,"ミッドナイト☆WAR[A]":2317,"花冠 feat.Aikapin[A]":2027,"龍王の霊廟(Mausoleum Of The Primal Dragon)[A]":2862,"EMERALDAS[H]":2036,"Fervidex[A]":2536,"HYPE THE CORE[A]":2637,"Temple of Anubis[A]":2193,"UMMU[A]":2656,"n'pa pa BBQ[A]":2541,"(This Is Not) The Angels[A]":2361,"Amazing Mirage[A]":2198,"Be A Star[A]":2573,"Beat Juggling Mix[A]":1787,"Beyond The Seven[A]":2459,"INVISIBLE STRIX[A]":2284,"Modular Technology[A]":2191,"PAPAYAPA BASS[A]":2485,"SAMURAI-Scramble[A]":1966,"nostos[A]":1117,"冬椿 ft. Kanae Asaba[L]":2729,"忍恋花[A]":2059,"鴉[A]":2538,"Daily Lunch Special[A]":2769,"GOBBLE[A]":1445,"On the FM[A]":2290,"Outbreak[A]":2726,"Rock It[A]":2489,"Routing[A]":2110,"SEITEN NO TERIYAKI[A]":2018,"SHELTER OF THE MIND[A]":2751,"STARLiGHT[A]":2544,"Uh-Oh[A]":2082,"灼熱 Pt.2 Long Train Running[H]":1769,"麗 ～うらら～[A]":2367,"AFRO KNUCKLE[A]":2106,"Chronos[L]":2468,"Discloze[A]":1979,"Erosion Mark[A]":2024,"Hello Happiness[A]":2037,"Line 4 Ruin[A]":2514,"No Tears[A]":2361,"Realize Maze[A]":2713,"Scarlet Moon[A]":2364,"とろぴかる倶楽部[A]":1836,"もっと！モット！ときめき feat. 松下[A]":2250,"パ→ピ→プ→Yeah![A]":2349,"ベィスドロップ・フリークス[L]":2024,"恋は白帯、サンシロー[L]":2571,"打打打打打打打打打打[A]":2153,"超青少年ノ為ノ超多幸ナ超古典的超舞曲[A]":2457,"ALBA -黎明-[A]":2931,"Critical Crystal[A]":2668,"Elektrick U-Phoria[A]":2788,"Element of SPADA[L]":2951,"Funny shuffle[A]":1004,"I will be back -オレは帰ってきた-[A]":2620,"Lighting Shower[A]":2132,"MAGIC &amp; LOVE[A]":2691,"Overload Frontier[A]":2053,"SCHWARZSCHILD FIELD[A]":972,"Unicorn tail[A]":2875,"VOX UP[H]":2408,"m1dy Deluxe[A]":2085,"rainbow guitar weeps[A]":2516,"refractive index[A]":2419,"バンブーソード・ガール[A]":2125,"405nm (Ryu☆mix)[A]":2318,"Beastie Starter[A]":1697,"Cookie Bouquets[A]":3220,"FLOWER[A]":2496,"Illegal Function Call[A]":1789,"Saturn[A]":2170,"VEGA[A]":2873,"examination leave[A]":3093,"カジノファイヤーことみちゃん[A]":2032,"朧[L]":2297,"532nm[A]":2443,"GIGANT[L]":2523,"In the Blackest Den[A]":2117,"SHADE[A]":2609,"ユミル[A]":2560,"蛇神[A]":2457,"BROKEN EDEN[A]":2074,"Believe In Me[A]":2187,"Bounce Bounce Bounce[A]":968,"Destiny Sword[A]":2160,"Kailua[A]":1851,"Sakura Reflection[A]":2240,"WISE UP![L]":2338,"旅人リラン[A]":2244,"D[A]":1663,"Elisha[A]":2032,"Empire State Glory[A]":2393,"Hydrogen Blueback[L]":1727,"MIRACLE MEETS[A]":2079,"NEW SENSATION -もう、あなたしか見えない-[A]":2415,"bloomin' feeling[A]":2361,"ALL MY TURN -このターンに、オレの全てを賭ける-[A]":2178,"Flash Back 90's[L]":2585,"Just a Little Smile[A]":897,"Marie Antoinette[A]":1923,"THE SHINING POLARIS(kors k mix)[A]":2823,"V2[A]":3105,"naughty girl@Queen's Palace[A]":1849,"naughty girl@Queen's Palace[L]":2167,"ミッドナイト堕天使[A]":2569,"凛として咲く花の如く[L]":2993,"2 tribe 4 K[A]":2518,"Anisakis -somatic mutation type\"Forza\"-[A]":2590,"Blue Rain[A]":2100,"Digitank System[A]":1783,"PARANOiA ～HADES～[H]":1016,"STEEL NEEDLE[A]":2128,"Wanna Party?[L]":2340,"four pieces of heaven[A]":1897,"in the Sky[A]":2387,"the trigger of innocence[L]":2921,"Blind Justice ～Torn souls, Hurt Faiths ～[A]":2344,"GOLD RUSH[A]":2014,"INORI[A]":2707,"KAMAITACHI[A]":2421,"Sense 2007[H]":1932,"TRANOID[A]":1883,"Broadbanded[A]":1803,"DEEP ROAR[A]":2480,"Ganymede[A]":1908,"Harmony and Lovely[A]":2056,"MINT[A]":2002,"Sun Field[A]":2197,"tripping contact(teranoid&amp;MC Natsack Remix)[A]":2117,"waxing and wanding[A]":2726,"嘆きの樹[H]":2287,"100％ minimoo-G[A]":1386,"Aurora[A]":2303,"EDEN[L]":3093,"INAZUMA[A]":2434,"Pollinosis[A]":2232,"Scripted Connection⇒ H mix[A]":2152,"Be quiet[A]":2005,"FAKE TIME[H]":1668,"GENOCIDE[A]":2005,"Secret of Love[A]":1878,"1st Samurai[A]":798,"Love Is Eternity[A]":2163,"Lucy[A]":2094,"RISLIM -Remix-[A]":1628,"SWEETEST SAVAGE[A]":1601,"quasar[A]":2148,"Blame[A]":1741,"Halfway of promise[A]":1620,"rainbow flyer[A]":1938,"Spica[A]":660,"stoic[A]":2286,"Buffalo[L]":1958,"Linus[A]":1960,"CHECKING YOU OUT[A]":1100,"Holic[A]":1572,"R5[A]":1684}