{"Banger Banger Banger Banger[A]":2715,"DREAM OF SPACE UFO ABDUCTION[A]":2570,"Ergosphere[A]":2553,"FINALLY BLAZE[A]":2633,"Game Changers[A]":2547,"Hat Surprise[A]":2317,"ILAYZA[A]":2643,"Lawes's Parotia[A]":2422,"Onyx[A]":2268,"SOLID WYVERN[A]":2488,"Souhait bleu[A]":2536,"Tail Lights[A]":2989,"Ventriloquist[A]":2312,"Victory Of Ravers[A]":2389,"Xyndrome[A]":2740,"kors k's How to make OTOGE CORE[A]":2138,"《GRANDMASTER》[A]":2751,"ぐだふわエブリデー[A]":2189,"ウツシミウツシ[A]":2993,"オールトの雲[A]":2515,"デモーニッシュ[A]":2227,"ハイテックトキオ[A]":2538,"ミュージック・アワー[A]":2842,"月とミルク[A]":2663,"青の洞窟[A]":2854,"Ah Hah Yeah[A]":2000,"Danza Aestas[A]":2854,"Dawn Saga[A]":2528,"Farewell to Marrakech[A]":2062,"Rejection Girl[A]":2565,"Sinus Iridum[H]":1773,"X-ray binary[A]":2667,"Zenith[A]":1923,"apo:llioth[A]":2712,"儚き恋の華[A]":2823,"無意識のフィロソフィア[A]":3184,"Bow shock!![A]":2938,"GIGA VIOLATE[A]":2533,"Theory[A]":2195,"シャムシールの舞[A]":2395,"ランカーキラーガール[A]":2824,"COSMIC CYBER[A]":2738,"LADYBIRD[A]":2260,"Night! Night! Night![A]":2779,"ROCK女 feat. 大山愛未, Ken[A]":2440,"Urban Constellations[A]":2119,"Yum Yum Jelly[A]":2214,"ZENDEGI DANCE[A]":2645,"ミッドナイト☆WAR[A]":2419,"泰東ノ翠霞[A]":1581,"龍王の霊廟(Mausoleum Of The Primal Dragon)[A]":3114,"Back Spin Sweeper[A]":2090,"FUTURE is Dead[A]":2054,"Fervidex[A]":2580,"Temple of Anubis[A]":2467,"UMMU[A]":2778,"Usual Days-remix[A]":2427,"(This Is Not) The Angels[A]":2484,"Macuilxochitl[A]":3131,"nostos[A]":2319,"忍恋花[A]":2151,"鴉[A]":2534,"Acid Pumper[A]":2298,"STARLIGHT DANCEHALL[A]":2481,"Beyond The Earth[A]":2897,"Discloze[A]":2399,"Scarlet Moon[A]":2547,"Scars of FAUNA[A]":2715,"パ→ピ→プ→Yeah![A]":2416,"ベィスドロップ・フリークス[L]":2109,"時空トラベローグ[A]":2466,"ALBA -黎明-[A]":3081,"Critical Crystal[A]":2669,"Dark Fall[A]":2537,"FLOWER[A]":2718,"カジノファイヤーことみちゃん[A]":2243,"24th Century BOY[A]":2658,"532nm[A]":2484,"ANTHEM LANDING[A]":2820,"Bounce Bounce Bounce[A]":2243,"Energy Drive[A]":2068,"Golden Palms[L]":2225,"Kailua[A]":2025,"Sakura Reflection[A]":2321,"ZETA～素数の世界と超越者～[A]":2950,"DROP[A]":2418,"MIRACLE MEETS[A]":2152,"Raison d'etre～交差する宿命～[A]":2540,"Just a Little Smile[A]":2149,"Secrets[A]":2859,"You'll say \"Now!\"[A]":2353,"天空脳番長危機十六連打[A]":2423,"MENTAL MELTDOWN[A]":2577,"four pieces of heaven[A]":2027,"Second Heaven[A]":2014,"smile[A]":2706,"tripping contact(teranoid&MC Natsack Remix)[A]":2260,"CaptivAte～浄化～[A]":2323,"ラクエン[A]":1843,"AGEHA[L]":2295,"BLOCKS[A]":1883,"Debtty Daddy[A]":2465,"quasar[A]":2214,"Blame[A]":1829,"Giudecca[A]":2541,"RUGGED ASH[L]":1891}