{"-65℃[A]":3393,"3!dolon Forc3[A]":2708,"ASIAN VIRTUAL REALITIES (MELTING TOGETHER IN DAZZLING DARKNESS)[A]":3022,"BIGソムタム[A]":3230,"BLACK or WHITE?[A]":3486,"COSMIC RAY[A]":2551,"DUAL STRIKER[A]":3536,"Empire of Fury[A]":3073,"Fire Beat[A]":2566,"Ignis†Irae[A]":3215,"LOCUS OF THE TRAVEL[A]":3000,"Level 3[A]":3018,"MEGAERA[A]":3018,"Parvati[A]":2608,"SOLID STATE SQUAD -RISEN RELIC REMIX-[A]":3010,"Sinus Iridum[A]":2574,"THE PEERLESS UNDER HEAVEN[A]":2945,"Tiempo Loco[A]":3454,"Viridian[A]":3152,"Vitrum[A]":3244,"innocent revolver[A]":3575,"rommmo[A]":3168,"∀[A]":3207,"スーパー戦湯ババンバーン[A]":3251,"ディスコルディア[A]":3140,"バッド・スイーツ、バッド・ドリーム[A]":3338,"世界の果てに約束の凱歌を -ReUnion-[A]":3488,"二人ノ廃城幽踊宴[A]":2454,"伐折羅-vajra-[A]":3358,"水鏡の異界[A]":2833,"閠槞彁の願い[A]":2856,"魔法のかくれんぼ[A]":2399,"AKASHIC BREAK[A]":3274,"BEAT PRISONER[A]":3309,"Dans la nuit de l'eternite[A]":2993,"Double Dribble[A]":3114,"EROICA[A]":3465,"Everlasting Message[A]":2256,"Friction[!]Function[A]":2997,"Inferno of Fomalhaut[A]":2619,"LASER CRUSTER (IGNITE REMIX)[A]":3066,"LIGHTNING STRIKES[A]":3098,"Level 2[A]":2611,"Lords Of The Roundtable[A]":2618,"Matt Silver[A]":3127,"Megalara Garuda[A]":2807,"ORCA[A]":3069,"Primitive Vibes[A]":2935,"Rave Patroller[A]":3232,"SCREW // owo // SCREW[A]":2734,"Smashing Wedge[A]":3435,"T-REX vs Velociraptor (In the Far east euphoria)[A]":2975,"TECHNO Style Essentials[A]":2637,"THE BRAVE MUST DIE[A]":3697,"THE F∀UST[A]":3156,"TRIUMPH[A]":3019,"Ypsilon[L]":3360,"がっつり陰キャ!? 怪盗いいんちょの億劫^^;[A]":3822,"ピアノ協奏曲第1番”蠍火” (BlackY Remix)[A]":3314,"深淵に捧ぐレクイエム[A]":2764,"華麗なる大犬円舞曲[A]":3083,"魅惑のYUMMYスイーツ[A]":2786,"Carmina[A]":2853,"Carry Me Away[A]":2962,"DRUNK MONKY[A]":2088,"Dr. Chemical & Killing Machine[A]":3145,"Drastic Dramatic[A]":3198,"EVANESCENT[A]":3216,"GENE[A]":4000,"GO OVER WITH GLARE -ROOTAGE 26-[A]":3613,"HARD BRAIN[A]":3509,"KILL EACH OTHER[A]":3572,"L.F.O[A]":3085,"LOST TECHNOLOGIE[A]":3179,"Lethal Weapon[A]":2947,"Level One[A]":1208,"Macho Monky[A]":2718,"ONIGOROSHI[A]":2572,"Painful Fate[A]":2951,"Please Welcome Mr.C[A]":2775,"Red. by Jack Trance[A]":3057,"THE DAY OF JUBILATIONS[A]":3195,"The Rebellion of Sequencer[A]":2789,"Trill auf G[A]":2892,"Unbelief[A]":2641,"Visterhv[A]":3388,"X-DEN[A]":3181,"Xlo[A]":3396,"dAuntl3ss[A]":3195,"ruin of opals[A]":2746,"voltississimo[A]":3274,"お菓子の王国[A]":3748,"抱きしめてモナムール[A]":3777,"最小三倍完全数[A]":2136,"金野火織の金色提言[A]":2767,"255[A]":2982,"AA -rebuild-[A]":3281,"ANCHOR[A]":3265,"Antigravity[A]":2831,"Arca[A]":2940,"Boomy and The Boost[A]":3241,"DEADHEAT[A]":3072,"DEATH†ZIGOQ ～怒りの高速爆走野郎～[A]":3465,"DropZ-Line-[A]":2730,"EMERALDAS[A]":2904,"Initiation[A]":3409,"Life Is A Game ft.DD\"ナカタ\"Metal[A]":3167,"NITROUS CANNON[A]":3253,"Papilio ulysses[A]":2571,"Persephone[A]":2795,"Rampage[A]":3504,"Raspberry Railgun[A]":2975,"The Chase[A]":1888,"Xperanza[A]":2968,"シムルグの目醒め[A]":2977,"東京神話[A]":2576,"神謳 -RESONANCE-[A]":3792,"#MAGiCVLGiRL_TRVP_B3VTZ[A]":3283,"Amazing Mirage[L]":3029,"Apocalypse[A]":3343,"Caterpillar[A]":2720,"DORNWALD ～Junge～[A]":3086,"ECHIDNA[A]":3004,"FUZIN RIZIN[A]":3533,"Go Ahead!![A]":2265,"GuNGNiR[L]":3502,"HADES[A]":2868,"Mare Nectaris[A]":2991,"Quakes[A]":2864,"RAIN[A]":3028,"Rave Cannon[A]":3153,"SAMURAI-Scramble[L]":2117,"SAY BAY[A]":2645,"Sky High[A]":3568,"Snakey Kung-fu[A]":3178,"Steel Edge[A]":3043,"Summerlights(IIDX Edition)[A]":2917,"Super Rush[A]":3410,"TOGAKUSHI[A]":2436,"Venom[A]":2978,"〆[A]":3521,"イザナミノナゲキ[A]":3073,"九尾狐夜行[A]":2768,"刃図羅[A]":3193,"火影[A]":2473,"焔極OVERKILL[A]":3026,"童話回廊[A]":2928,"199024club -Re:BounceKiller-[A]":1999,"AO-1[A]":2539,"Blue Spring Express[A]":2911,"CODE:1 [revision1.0.1][A]":2839,"DIAMOND CROSSING[A]":2818,"Devil's Gear[A]":3194,"Dynamite[A]":3585,"Godspeed[A]":2791,"Grand Chariot[A]":3024,"Highcharge Divolt[A]":2557,"Konzert V[A]":3107,"M4K3 1T B0UNC3[A]":2867,"NINJA IS DEAD IIDX ver.[A]":2894,"NZM[A]":3000,"Nightmare before oversleep[A]":2786,"POSSESSION[A]":2794,"STARLIGHT DANCEHALL[L]":3101,"StrayedCatz[A]":2491,"Triple Counter[A]":3582,"Welcome[L]":3077,"X[A]":3417,"ZEPHYRANTHES[A]":3570,"refrain[A]":3369,"めいさいアイドル☆あいむちゃん♪[A]":3180,"灼熱 Pt.2 Long Train Running[A]":2700,"真 地獄超特急 -HELL or HELL-[A]":2899,"紫陽花 -AZISAI-[A]":2605,"駅猫のワルツ[A]":2398,"BLUE MIRAGE[A]":2630,"Beat Radiance[L]":3453,"Broken Sword[A]":3509,"CHRONO DIVER -NORNIR-[L]":3911,"Chrono Diver -PENDULUMs-[A]":3374,"Cosmic Cat[L]":3035,"Despair of ELFERIA[A]":3811,"EBONY & IVORY[A]":2749,"FANTASTIC THREE[A]":2894,"Flashes[A]":2895,"Gravigazer[A]":2787,"IMPLANTATION[A]":1967,"Invitation from Mr.C[A]":2553,"Monopole.[A]":3041,"NEO GENERATOR SEVEN[A]":3117,"Rave*it!! Rave*it!! [A]":3004,"Reflux[A]":2726,"Say YEEEAHH[A]":3015,"Shooting Fireball[A]":3573,"Sounds Of Summer [A]":2790,"SpaceLand☆TOYBOX[A]":2723,"Symmetry[A]":3111,"TIEFSEE[A]":3310,"TOXIC VIBRATION[A]":3392,"The Least 100sec[A]":2661,"We're so Happy (P*Light Remix) IIDX ver.[A]":3432,"ZZ[A]":2927,"cinder[A]":2872,"entelecheia[A]":3114,"それは花火のような恋[A]":3636,"リリーゼと炎龍レーヴァテイン[A]":3217,"共鳴遊戯の華[A]":3104,"千年ノ理[L]":3893,"少年は空を辿る[A]":3033,"紅牡丹[A]":2725,"表裏一体！？怪盗いいんちょの悩み[A]":3400,"超青少年ノ為ノ超多幸ナ超古典的超舞曲[L]":3816,"Adularia[A]":2652,"Ancient Scapes[A]":3247,"Ancient Scapes[L]":3540,"BLUE DRAGON(雷龍RemixIIDX)[A]":3045,"Close the World feat.a☆ru[A]":3103,"Close the World feat.a☆ru[L]":3242,"DARK LEGACY[A]":3326,"Feel The Beat[A]":3314,"Feel The Beat[L]":3627,"INSOMNIA[A]":2957,"IX[A]":3154,"Idola [A]":3168,"KAISER PHOENIX[A]":2980,"KAISER PHOENIX[L]":3300,"Last Dance[A]":3067,"PUNISHER[A]":3240,"Sigmund[A]":3275,"Sigmund[L]":3509,"VOX UP[A]":3196,"Verflucht[A]":3149,"Verflucht[L]":3794,"invoker[A]":3007,"invoker[L]":3275,"ra'am[A]":2413,"廿[L]":3013,"旋律のドグマ～Miserables～[A]":3623,"海神[A]":2910,"煉獄のエルフェリア[A]":3510,"疾風迅雷[A]":2663,"疾風迅雷[L]":2475,"轟け！恋のビーンボール！！[A]":3187,"Confiserie[A]":3129,"DAY DREAM[A]":1640,"Devilz Staircase[A]":2931,"Elemental Creation[A]":3592,"GAIA[A]":3024,"Hollywood Galaxy[A]":2487,"JOMANDA[A]":3164,"Liberation[A]":3532,"Little Star[A]":2924,"Plan 8[A]":2773,"Proof of the existence[A]":2957,"STULTI[A]":2364,"SYNC-ANTHEM[A]":3403,"Sol Cosine Job 2[A]":2927,"Thor's Hammer[A]":2378,"Timepiece phase II[A]":2961,"Timepiece phase II (CN Ver.)[A]":2591,"True Blue[A]":3522,"Valanga[A]":3019,"ΕΛΠΙΣ[L]":3243,"†渚の小悪魔ラヴリィ～レイディオ†(IIDX EDIT)[A]":3199,"お米の美味しい炊き方、そしてお米を食べることによるその効果。[A]":3090,"たまゆら[A]":2606,"アストライアの双皿[A]":2870,"キャトられ恋はモ～モク[A]":3416,"シュレーディンガーの猫[A]":3148,"トリカゴノ鳳凰[A]":3442,"仮想空間の旅人たち[A]":3697,"即席！脳直★ミュージックシステム[A]":3318,"狂イ咲ケ焔ノ華[A]":3389,"音楽[A]":2416,"龍と少女とデコヒーレンス[L]":3132,"BLACK.by X-Cross Fade[A]":3027,"DIAVOLO[A]":2170,"F[A]":3406,"HAERETICUS[A]":2748,"NNRT[A]":3230,"QUANTUM TELEPORTATION[L]":3377,"Snake Stick[A]":2398,"TITANS RETURN[A]":2238,"The Limbo[A]":3037,"The Sampling Paradise[A]":2847,"Thunderbolt[A]":3460,"Todestrieb[A]":3169,"WONDER WALKER[A]":3529,"YAKSHA[A]":3493,"fffff[A]":2904,"quaver♪[A]":3261,"天空の夜明け[A]":3477,"子供の落書き帳[A]":2294,"恋する☆宇宙戦争っ！！[A]":3301,"聖人の塔[A]":2682,"ALBIDA[A]":2802,"Broken[A]":2984,"Dances with Snow Fairies[A]":2831,"Session 9 -Chronicles-[A]":2945,"Watch Out Pt.2[A]":2502,"perditus†paradisus[A]":3066,"reunion[A]":2935,"sakura storm[A]":2265,"灼熱Beach Side Bunny[A]":2573,"AIR RAID FROM THA UNDAGROUND[L]":2534,"Almagest[A]":1776,"Bad Maniacs[A]":2946,"DOMINION[A]":3007,"EXUSIA[A]":3416,"Evans[A]":2564,"G59[A]":3467,"GOLDEN CROSS[A]":3272,"Red. by Full Metal Jacket[A]":2861,"SOLID STATE SQUAD[A]":3271,"SOLID STATE SQUAD[L]":3357,"eRAseRmOToRpHAntOM[A]":2998,"mosaic[A]":2947,"quell～the seventh slave～[A]":2946,"ワルツ第17番 ト短調”大犬のワルツ”[A]":2829,"3y3s[A]":3115,"Arabian Rave Night[L]":3358,"BITTER CHOCOLATE STRIKER[A]":3738,"Colorful Cookie[A]":3299,"Go Beyond!![A]":1904,"Marie Antoinette[L]":3040,"Secrets[A]":3788,"THANK YOU FOR PLAYING[L]":2705,"Y&Co. is dead or alive[A]":2537,"thunder HOUSE NATION Remix[L]":3664,"不沈艦CANDY[A]":3054,"卑弥呼[A]":3252,"Anisakis -somatic mutation type\"Forza\"-[L]":3437,"Blue Rain[L]":3111,"ICARUS[A]":2039,"ICARUS[L]":2142,"MENDES[A]":3198,"PARANOiA ～HADES～[A]":2401,"Ristaccia[A]":2638,"STEEL NEEDLE[L]":2776,"THE DEEP STRIKER[L]":3320,"TROOPERS[A]":2828,"Ubertreffen[L]":3030,"少年A[A]":2591,"Candy Galy[A]":3339,"FIRE FIRE[A]":2613,"Fascination MAXX[A]":2127,"GRID KNIGHT[L]":3358,"KAMAITACHI[L]":3190,"LASER CRUSTER[A]":3012,"Sense 2007[A]":2689,"TRANOID[A]":2497,"VANESSA[A]":2231,"VANESSA[L]":2762,"snow storm[A]":3221,"電人、暁に斃れる。[A]":3114,"CONTRACT[L]":2553,"DUE TOMORROW[A]":1749,"Ganymede[L]":2266,"waxing and wanding[L]":3775,"カゴノトリ～弐式～[A]":2540,"嘆きの樹[A]":3449,"SCREAM SQUAD[A]":1921,"Scripted Connection⇒ A mix[A]":2925,"Twelfth Style[L]":3007,"rage against usual[A]":2716,"冥[A]":2969,"AA[A]":3445,"Be quiet[A]":2456,"FAKE TIME[A]":2250,"RED ZONE[L]":2927,"gigadelic[H]":2013,"gigadelic[A]":2366,"spiral galaxy[L]":3547,"ピアノ協奏曲第１番”蠍火”[A]":2451,"Innocent Walls[H]":2342,"Innocent Walls[A]":2623,"One More Lovely[A]":2583,"雪月花[A]":2353,"moon_child[A]":2406,"one or eight[A]":2125,"PLEASE DON'T GO[A]":2231,"桜[A]":1869,"A[A]":2296,"Colors (radio edit)[A]":2299,"V[A]":2816}