{"ABSOLUTE (kors k Remix)[A]":2445,"AMRITA -不滅ノ花-[A]":2647,"Ah Hah Yeah[A]":1988,"Breakin' Rules[A]":2662,"Burning Flame[A]":2708,"Crazy Jackpot[A]":2695,"Dawn Saga[A]":2531,"Farewell to Marrakech[A]":2091,"GIGA RAID[A]":2298,"Jungle Eater[A]":2775,"LAST DAY[A]":2937,"Lovely Howdy Cowboy!![A]":2666,"Neo Heritage[A]":2707,"Ocean Blue feat. Luschel[A]":2386,"Overslept[A]":2444,"POLKAMAИIA[A]":2749,"Para siempre[A]":2741,"Romanticが止まらない[A]":2651,"Rubrum Piano[A]":2360,"Swarm Of Scarabs[A]":2243,"X-ray binary[A]":2690,"apo:llioth[A]":2802,"of the first magnitude[A]":2829,"乱膳の舞姫[A]":2564,"儚き恋の華[A]":2761,"涙のテ・エストラーニョ・ムーチョ[A]":2662,"Moving on[A]":2862,"S!ck (Nhato Remix)[A]":2454,"Shiva[A]":2018,"Theory[A]":2410,"UNITE THE HEART[A]":3179,"VALKYRIAS -英雄誕生-[A]":2625,"ランカーキラーガール[A]":2721,"COSMIC CYBER[A]":2761,"ROCK女 feat. 大山愛未, Ken[A]":2378,"U.S.A.[A]":2754,"Wolf 1061[A]":2955,"XENON II ～TOMOYUKIの野望～[A]":2818,"Yum Yum Jelly[A]":2240,"Back Spin Sweeper[A]":2099,"Battleground[A]":2495,"Be a Hero![A]":2975,"Exhaust Hype[A]":2638,"HYPE THE CORE[A]":2820,"Nothing but Theory[A]":2737,"THE CANNONBALLER[A]":3249,"Temple of Anubis[A]":2442,"UMMU[A]":2877,"Usual Days-remix[A]":2508,"バ→ビ→ブ→Bomb![A]":2326,"(This Is Not) The Angels[A]":2515,"AsiaN distractive[A]":2492,"Beat Juggling Mix[A]":2024,"BroGamer[A]":2947,"Egret and Willow[A]":2565,"SAMURAI-Scramble[L]":2252,"SEQUENCE CAT[A]":2724,"XINOBIKILL[A]":2699,"crew[A]":2812,"忍恋花[A]":2039,"鴉[A]":2624,"Acid Pumper[A]":2273,"Battle Train -IIDX Edition-[A]":3018,"Journey[L]":3003,"Critical Crystal[A]":2765,"MAGIC & LOVE[A]":2783,"S!ck[A]":2523,"TITANS RETURN[L]":2366,"Aegis[A]":2151,"Believe In Me[A]":2262,"Kailua[A]":1999,"Elisha[A]":2131,"bloomin' feeling[A]":2462,"Bahram Attack-猫叉Master Remix-[A]":3140,"Kung-fu Empire[L]":3101,"Secrets[A]":3015,"V2[A]":3306,"naughty girl@Queen's Palace[L]":1984,"Anisakis -somatic mutation type\"Forza\"-[L]":2742,"Blue Rain[L]":2174,"Digitank System[A]":1971,"MENTAL MELTDOWN[A]":2581,"STEEL NEEDLE[L]":2293,"State Of The Art[A]":2965,"Wanna Party?[L]":2483,"four pieces of heaven[A]":2089,"KAMAITACHI[L]":2554,"the shadow[A]":2761,"CONTRACT[L]":1970,"Aurora[A]":2179,"BLOCKS[A]":1839,"GENOCIDE[A]":2268,"No.13[A]":2909,"Giudecca[A]":2490,"xenon[A]":2578,"CHECKING YOU OUT[A]":1227}